{"squad_value_m": 50.92, "avg_player_value_m": 1.96, "avg_age": 29.7, "squad_size": 26, "top_players": [{"name": "Logan Costa", "position": "Centre-Back", "value_m": 15.0}, {"name": "Bruno Varela", "position": "Goalkeeper", "value_m": 4.0}, {"name": "Kevin Lenini", "position": "Defensive Midfield", "value_m": 3.5}, {"name": "Wagner Pina", "position": "Right-Back", "value_m": 3.0}, {"name": "Hélio Varela", "position": "Left Winger", "value_m": 2.0}], "injured": [], "suspended": [], "available_value_m": 50.92, "availability_pct": 1.0, "club_season": {}, "source": "transfermarkt"}