[
  {
    "tm_player_id": 348144,
    "espn_player_id": null,
    "name": "Bechir Ben Said",
    "slug": "bechir-ben-said",
    "position": "Goalkeeper",
    "age": 32,
    "market_value_m": 0.8,
    "fdorg_team_id": 802,
    "team_name": "Tunisia",
    "club_season": {
      "apps": 34,
      "minutes": 3060,
      "goals": 0,
      "assists": 0,
      "yellows": 2,
      "reds": 0,
      "goals_per_90": 0.0,
      "assists_per_90": 0.0,
      "form_score": 0.0
    }
  },
  {
    "tm_player_id": 569433,
    "espn_player_id": null,
    "name": "Aymen Dahmen",
    "slug": "aymen-dahmen",
    "position": "Goalkeeper",
    "age": 27,
    "market_value_m": 0.65,
    "fdorg_team_id": 802,
    "team_name": "Tunisia",
    "club_season": {
      "apps": 28,
      "minutes": 2550,
      "goals": 0,
      "assists": 0,
      "yellows": 1,
      "reds": 0,
      "goals_per_90": 0.0,
      "assists_per_90": 0.0,
      "form_score": 0.0
    }
  },
  {
    "tm_player_id": 679463,
    "espn_player_id": null,
    "name": "Noureddine Farhati",
    "slug": "noureddine-farhati",
    "position": "Goalkeeper",
    "age": 24,
    "market_value_m": 0.3,
    "fdorg_team_id": 802,
    "team_name": "Tunisia",
    "club_season": {
      "apps": 33,
      "minutes": 3000,
      "goals": 0,
      "assists": 0,
      "yellows": 0,
      "reds": 0,
      "goals_per_90": 0.0,
      "assists_per_90": 0.0,
      "form_score": 0.0
    }
  },
  {
    "tm_player_id": 295381,
    "espn_player_id": null,
    "name": "Sabri Ben Hessen",
    "slug": "sabri-ben-hessen",
    "position": "Goalkeeper",
    "age": 28,
    "market_value_m": 0.3,
    "fdorg_team_id": 802,
    "team_name": "Tunisia",
    "club_season": {
      "apps": 32,
      "minutes": 2865,
      "goals": 0,
      "assists": 0,
      "yellows": 1,
      "reds": 0,
      "goals_per_90": 0.0,
      "assists_per_90": 0.0,
      "form_score": 0.0
    }
  },
  {
    "tm_player_id": 206758,
    "espn_player_id": null,
    "name": "Sami Helal",
    "slug": "sami-helal",
    "position": "Goalkeeper",
    "age": 36,
    "market_value_m": 0.175,
    "fdorg_team_id": 802,
    "team_name": "Tunisia",
    "club_season": {
      "apps": 23,
      "minutes": 2054,
      "goals": 0,
      "assists": 0,
      "yellows": 0,
      "reds": 0,
      "goals_per_90": 0.0,
      "assists_per_90": 0.0,
      "form_score": 0.0
    }
  },
  {
    "tm_player_id": 441867,
    "espn_player_id": null,
    "name": "Abdessalem Hallaoui",
    "slug": "abdessalem-hallaoui",
    "position": "Goalkeeper",
    "age": 35,
    "market_value_m": 0.1,
    "fdorg_team_id": 802,
    "team_name": "Tunisia",
    "club_season": {
      "apps": 33,
      "minutes": 2970,
      "goals": 0,
      "assists": 0,
      "yellows": 3,
      "reds": 0,
      "goals_per_90": 0.0,
      "assists_per_90": 0.0,
      "form_score": 0.0
    }
  },
  {
    "tm_player_id": 496706,
    "espn_player_id": null,
    "name": "Montassar Talbi",
    "slug": "montassar-talbi",
    "position": "Centre-Back",
    "age": 26,
    "market_value_m": 5.0,
    "fdorg_team_id": 802,
    "team_name": "Tunisia",
    "club_season": {
      "apps": 31,
      "minutes": 2790,
      "goals": 0,
      "assists": 1,
      "yellows": 4,
      "reds": 0,
      "goals_per_90": 0.0,
      "assists_per_90": 0.032,
      "form_score": 0.032
    }
  },
  {
    "tm_player_id": 306330,
    "espn_player_id": null,
    "name": "Yassine Meriah",
    "slug": "yassine-meriah",
    "position": "Centre-Back",
    "age": 31,
    "market_value_m": 1.5,
    "fdorg_team_id": 802,
    "team_name": "Tunisia",
    "club_season": {
      "apps": 25,
      "minutes": 2146,
      "goals": 2,
      "assists": 0,
      "yellows": 3,
      "reds": 0,
      "goals_per_90": 0.084,
      "assists_per_90": 0.0,
      "form_score": 0.084
    }
  },
  {
    "tm_player_id": 657796,
    "espn_player_id": null,
    "name": "Alaa Ghram",
    "slug": "alaa-ghram",
    "position": "Centre-Back",
    "age": 23,
    "market_value_m": 1.5,
    "fdorg_team_id": 802,
    "team_name": "Tunisia",
    "club_season": {
      "apps": 17,
      "minutes": 1162,
      "goals": 1,
      "assists": 0,
      "yellows": 0,
      "reds": 1,
      "goals_per_90": 0.077,
      "assists_per_90": 0.0,
      "form_score": 0.077
    }
  },
  {
    "tm_player_id": 450417,
    "espn_player_id": null,
    "name": "Dylan Bronn",
    "slug": "dylan-bronn",
    "position": "Centre-Back",
    "age": 29,
    "market_value_m": 1.3,
    "fdorg_team_id": 802,
    "team_name": "Tunisia",
    "club_season": {
      "apps": 22,
      "minutes": 1818,
      "goals": 1,
      "assists": 1,
      "yellows": 7,
      "reds": 0,
      "goals_per_90": 0.05,
      "assists_per_90": 0.05,
      "form_score": 0.099
    }
  },
  {
    "tm_player_id": 275956,
    "espn_player_id": null,
    "name": "Nader Ghandri",
    "slug": "nader-ghandri",
    "position": "Centre-Back",
    "age": 29,
    "market_value_m": 0.9,
    "fdorg_team_id": 802,
    "team_name": "Tunisia",
    "club_season": {
      "apps": 36,
      "minutes": 2987,
      "goals": 1,
      "assists": 1,
      "yellows": 10,
      "reds": 0,
      "goals_per_90": 0.03,
      "assists_per_90": 0.03,
      "form_score": 0.06
    }
  },
  {
    "tm_player_id": 454494,
    "espn_player_id": null,
    "name": "Hamza Ben Abda",
    "slug": "hamza-ben-abda",
    "position": "Centre-Back",
    "age": 29,
    "market_value_m": 0.7,
    "fdorg_team_id": 802,
    "team_name": "Tunisia",
    "club_season": {
      "apps": 29,
      "minutes": 2610,
      "goals": 0,
      "assists": 0,
      "yellows": 5,
      "reds": 0,
      "goals_per_90": 0.0,
      "assists_per_90": 0.0,
      "form_score": 0.0
    }
  },
  {
    "tm_player_id": 244044,
    "espn_player_id": null,
    "name": "Hamza Jelassi",
    "slug": "hamza-jelassi",
    "position": "Centre-Back",
    "age": 33,
    "market_value_m": 0.45,
    "fdorg_team_id": 802,
    "team_name": "Tunisia",
    "club_season": {
      "apps": 38,
      "minutes": 3187,
      "goals": 6,
      "assists": 1,
      "yellows": 9,
      "reds": 0,
      "goals_per_90": 0.169,
      "assists_per_90": 0.028,
      "form_score": 0.198
    }
  },
  {
    "tm_player_id": 191407,
    "espn_player_id": null,
    "name": "Oussama Haddadi",
    "slug": "oussama-haddadi",
    "position": "Centre-Back",
    "age": 32,
    "market_value_m": 0.4,
    "fdorg_team_id": 802,
    "team_name": "Tunisia",
    "club_season": {
      "apps": 26,
      "minutes": 1967,
      "goals": 0,
      "assists": 1,
      "yellows": 1,
      "reds": 0,
      "goals_per_90": 0.0,
      "assists_per_90": 0.046,
      "form_score": 0.046
    }
  },
  {
    "tm_player_id": 295428,
    "espn_player_id": null,
    "name": "Marouane Sahraoui",
    "slug": "marouane-sahraoui",
    "position": "Centre-Back",
    "age": 28,
    "market_value_m": 0.4,
    "fdorg_team_id": 802,
    "team_name": "Tunisia",
    "club_season": {
      "apps": 28,
      "minutes": 2454,
      "goals": 0,
      "assists": 0,
      "yellows": 5,
      "reds": 0,
      "goals_per_90": 0.0,
      "assists_per_90": 0.0,
      "form_score": 0.0
    }
  },
  {
    "tm_player_id": 1071742,
    "espn_player_id": null,
    "name": "Adem Arous",
    "slug": "adem-arous",
    "position": "Centre-Back",
    "age": 20,
    "market_value_m": 0.2,
    "fdorg_team_id": 802,
    "team_name": "Tunisia",
    "club_season": {
      "apps": 25,
      "minutes": 1998,
      "goals": 2,
      "assists": 1,
      "yellows": 2,
      "reds": 0,
      "goals_per_90": 0.09,
      "assists_per_90": 0.045,
      "form_score": 0.135
    }
  },
  {
    "tm_player_id": 211474,
    "espn_player_id": null,
    "name": "Ali Abdi",
    "slug": "ali-abdi",
    "position": "Left-Back",
    "age": 31,
    "market_value_m": 3.0,
    "fdorg_team_id": 802,
    "team_name": "Tunisia",
    "club_season": {
      "apps": 32,
      "minutes": 1657,
      "goals": 3,
      "assists": 0,
      "yellows": 2,
      "reds": 1,
      "goals_per_90": 0.163,
      "assists_per_90": 0.0,
      "form_score": 0.163
    }
  },
  {
    "tm_player_id": 454495,
    "espn_player_id": null,
    "name": "Mohamed Amine Ben Hamida",
    "slug": "mohamed-amine-ben-hamida",
    "position": "Left-Back",
    "age": 29,
    "market_value_m": 0.65,
    "fdorg_team_id": 802,
    "team_name": "Tunisia",
    "club_season": {
      "apps": 38,
      "minutes": 3220,
      "goals": 1,
      "assists": 3,
      "yellows": 4,
      "reds": 0,
      "goals_per_90": 0.028,
      "assists_per_90": 0.084,
      "form_score": 0.112
    }
  },
  {
    "tm_player_id": 133042,
    "espn_player_id": null,
    "name": "Ali Maâloul",
    "slug": "ali-maaloul",
    "position": "Left-Back",
    "age": 34,
    "market_value_m": 0.5,
    "fdorg_team_id": 802,
    "team_name": "Tunisia",
    "club_season": {
      "apps": 27,
      "minutes": 2276,
      "goals": 3,
      "assists": 7,
      "yellows": 0,
      "reds": 0,
      "goals_per_90": 0.119,
      "assists_per_90": 0.277,
      "form_score": 0.395
    }
  },
  {
    "tm_player_id": 406008,
    "espn_player_id": null,
    "name": "Yan Valery",
    "slug": "yan-valery",
    "position": "Right-Back",
    "age": 25,
    "market_value_m": 1.0,
    "fdorg_team_id": 802,
    "team_name": "Tunisia",
    "club_season": {
      "apps": 37,
      "minutes": 2993,
      "goals": 0,
      "assists": 4,
      "yellows": 5,
      "reds": 0,
      "goals_per_90": 0.0,
      "assists_per_90": 0.12,
      "form_score": 0.12
    }
  },
  {
    "tm_player_id": 1034598,
    "espn_player_id": null,
    "name": "Moutaz Neffati",
    "slug": "moutaz-neffati",
    "position": "Right-Back",
    "age": 20,
    "market_value_m": 0.8,
    "fdorg_team_id": 802,
    "team_name": "Tunisia",
    "club_season": {
      "apps": 11,
      "minutes": 833,
      "goals": 2,
      "assists": 0,
      "yellows": 2,
      "reds": 0,
      "goals_per_90": 0.216,
      "assists_per_90": 0.0,
      "form_score": 0.216
    }
  },
  {
    "tm_player_id": 290406,
    "espn_player_id": null,
    "name": "Mohamed Ben Ali",
    "slug": "mohamed-ben-ali",
    "position": "Right-Back",
    "age": 29,
    "market_value_m": 0.5,
    "fdorg_team_id": 802,
    "team_name": "Tunisia",
    "club_season": {
      "apps": 26,
      "minutes": 1883,
      "goals": 1,
      "assists": 1,
      "yellows": 5,
      "reds": 0,
      "goals_per_90": 0.048,
      "assists_per_90": 0.048,
      "form_score": 0.096
    }
  },
  {
    "tm_player_id": 966603,
    "espn_player_id": null,
    "name": "Mahmoud Ghorbel",
    "slug": "mahmoud-ghorbel",
    "position": "Right-Back",
    "age": 21,
    "market_value_m": 0.45,
    "fdorg_team_id": 802,
    "team_name": "Tunisia",
    "club_season": {
      "apps": 19,
      "minutes": 1354,
      "goals": 0,
      "assists": 2,
      "yellows": 5,
      "reds": 0,
      "goals_per_90": 0.0,
      "assists_per_90": 0.133,
      "form_score": 0.133
    }
  },
  {
    "tm_player_id": 898076,
    "espn_player_id": null,
    "name": "Houssem Hassen Romdhane",
    "slug": "houssem-hassen-romdhane",
    "position": "Right-Back",
    "age": 24,
    "market_value_m": 0.2,
    "fdorg_team_id": 802,
    "team_name": "Tunisia",
    "club_season": {
      "apps": 5,
      "minutes": 222,
      "goals": 1,
      "assists": 0,
      "yellows": 2,
      "reds": 0,
      "goals_per_90": 0.405,
      "assists_per_90": 0.0,
      "form_score": 0.405
    }
  },
  {
    "tm_player_id": 290587,
    "espn_player_id": null,
    "name": "Ellyes Skhiri",
    "slug": "ellyes-skhiri",
    "position": "Defensive Midfield",
    "age": 29,
    "market_value_m": 9.0,
    "fdorg_team_id": 802,
    "team_name": "Tunisia",
    "club_season": {
      "apps": 34,
      "minutes": 1854,
      "goals": 0,
      "assists": 0,
      "yellows": 1,
      "reds": 1,
      "goals_per_90": 0.0,
      "assists_per_90": 0.0,
      "form_score": 0.0
    }
  },
  {
    "tm_player_id": 673513,
    "espn_player_id": null,
    "name": "Mohamed Belhadj Mahmoud",
    "slug": "mohamed-belhadj-mahmoud",
    "position": "Defensive Midfield",
    "age": 24,
    "market_value_m": 3.0,
    "fdorg_team_id": 802,
    "team_name": "Tunisia",
    "club_season": {
      "apps": 35,
      "minutes": 1741,
      "goals": 2,
      "assists": 1,
      "yellows": 6,
      "reds": 0,
      "goals_per_90": 0.103,
      "assists_per_90": 0.052,
      "form_score": 0.155
    }
  },
  {
    "tm_player_id": 781998,
    "espn_player_id": null,
    "name": "Moez Haj Ali",
    "slug": "moez-haj-ali",
    "position": "Defensive Midfield",
    "age": 25,
    "market_value_m": 0.6,
    "fdorg_team_id": 802,
    "team_name": "Tunisia",
    "club_season": {
      "apps": 38,
      "minutes": 2429,
      "goals": 6,
      "assists": 5,
      "yellows": 3,
      "reds": 0,
      "goals_per_90": 0.222,
      "assists_per_90": 0.185,
      "form_score": 0.408
    }
  },
  {
    "tm_player_id": 233782,
    "espn_player_id": null,
    "name": "Aïssa Laïdouni",
    "slug": "aissa-laidouni",
    "position": "Central Midfield",
    "age": 28,
    "market_value_m": 5.0,
    "fdorg_team_id": 802,
    "team_name": "Tunisia",
    "club_season": {
      "apps": 22,
      "minutes": 1869,
      "goals": 1,
      "assists": 5,
      "yellows": 3,
      "reds": 0,
      "goals_per_90": 0.048,
      "assists_per_90": 0.241,
      "form_score": 0.289
    }
  },
  {
    "tm_player_id": 546712,
    "espn_player_id": null,
    "name": "Anis Ben Slimane",
    "slug": "anis-ben-slimane",
    "position": "Central Midfield",
    "age": 23,
    "market_value_m": 2.5,
    "fdorg_team_id": 802,
    "team_name": "Tunisia",
    "club_season": {
      "apps": 26,
      "minutes": 1372,
      "goals": 5,
      "assists": 6,
      "yellows": 4,
      "reds": 0,
      "goals_per_90": 0.328,
      "assists_per_90": 0.394,
      "form_score": 0.722
    }
  },
  {
    "tm_player_id": 577881,
    "espn_player_id": null,
    "name": "Mohamed Ali Ben Romdhane",
    "slug": "mohamed-ali-ben-romdhane",
    "position": "Central Midfield",
    "age": 25,
    "market_value_m": 2.0,
    "fdorg_team_id": 802,
    "team_name": "Tunisia",
    "club_season": {
      "apps": 33,
      "minutes": 1811,
      "goals": 1,
      "assists": 4,
      "yellows": 2,
      "reds": 0,
      "goals_per_90": 0.05,
      "assists_per_90": 0.199,
      "form_score": 0.248
    }
  },
  {
    "tm_player_id": 191903,
    "espn_player_id": null,
    "name": "Ferjani Sassi",
    "slug": "ferjani-sassi",
    "position": "Central Midfield",
    "age": 32,
    "market_value_m": 1.4,
    "fdorg_team_id": 802,
    "team_name": "Tunisia",
    "club_season": {
      "apps": 29,
      "minutes": 2490,
      "goals": 8,
      "assists": 2,
      "yellows": 6,
      "reds": 0,
      "goals_per_90": 0.289,
      "assists_per_90": 0.072,
      "form_score": 0.361
    }
  },
  {
    "tm_player_id": 581156,
    "espn_player_id": null,
    "name": "Houssem Tka",
    "slug": "houssem-tka",
    "position": "Central Midfield",
    "age": 24,
    "market_value_m": 1.2,
    "fdorg_team_id": 802,
    "team_name": "Tunisia",
    "club_season": {
      "apps": 41,
      "minutes": 3098,
      "goals": 3,
      "assists": 1,
      "yellows": 5,
      "reds": 0,
      "goals_per_90": 0.087,
      "assists_per_90": 0.029,
      "form_score": 0.116
    }
  },
  {
    "tm_player_id": 388220,
    "espn_player_id": null,
    "name": "Sayfallah Ltaief",
    "slug": "sayfallah-ltaief",
    "position": "Left Midfield",
    "age": 24,
    "market_value_m": 2.0,
    "fdorg_team_id": 802,
    "team_name": "Tunisia",
    "club_season": {
      "apps": 27,
      "minutes": 1595,
      "goals": 3,
      "assists": 2,
      "yellows": 0,
      "reds": 0,
      "goals_per_90": 0.169,
      "assists_per_90": 0.113,
      "form_score": 0.282
    }
  },
  {
    "tm_player_id": 782935,
    "espn_player_id": null,
    "name": "Amin Cherni",
    "slug": "amin-cherni",
    "position": "Left Midfield",
    "age": 23,
    "market_value_m": 1.0,
    "fdorg_team_id": 802,
    "team_name": "Tunisia",
    "club_season": {
      "apps": 35,
      "minutes": 3033,
      "goals": 0,
      "assists": 4,
      "yellows": 2,
      "reds": 0,
      "goals_per_90": 0.0,
      "assists_per_90": 0.119,
      "form_score": 0.119
    }
  },
  {
    "tm_player_id": 607224,
    "espn_player_id": null,
    "name": "Hannibal",
    "slug": "hannibal",
    "position": "Attacking Midfield",
    "age": 21,
    "market_value_m": 9.0,
    "fdorg_team_id": 802,
    "team_name": "Tunisia",
    "club_season": {
      "apps": 30,
      "minutes": 1369,
      "goals": 1,
      "assists": 4,
      "yellows": 11,
      "reds": 0,
      "goals_per_90": 0.066,
      "assists_per_90": 0.263,
      "form_score": 0.329
    }
  },
  {
    "tm_player_id": 295382,
    "espn_player_id": null,
    "name": "Firas Ben Larbi",
    "slug": "firas-ben-larbi",
    "position": "Attacking Midfield",
    "age": 28,
    "market_value_m": 4.5,
    "fdorg_team_id": 802,
    "team_name": "Tunisia",
    "club_season": {
      "apps": 32,
      "minutes": 1509,
      "goals": 3,
      "assists": 5,
      "yellows": 3,
      "reds": 0,
      "goals_per_90": 0.179,
      "assists_per_90": 0.298,
      "form_score": 0.477
    }
  },
  {
    "tm_player_id": 295409,
    "espn_player_id": null,
    "name": "Chiheb Jebali",
    "slug": "chiheb-jebali",
    "position": "Attacking Midfield",
    "age": 28,
    "market_value_m": 0.85,
    "fdorg_team_id": 802,
    "team_name": "Tunisia",
    "club_season": {
      "apps": 42,
      "minutes": 2771,
      "goals": 2,
      "assists": 6,
      "yellows": 8,
      "reds": 0,
      "goals_per_90": 0.065,
      "assists_per_90": 0.195,
      "form_score": 0.26
    }
  },
  {
    "tm_player_id": 810096,
    "espn_player_id": null,
    "name": "Ismaël Gharbi",
    "slug": "ismael-gharbi",
    "position": "Left Winger",
    "age": 20,
    "market_value_m": 7.5,
    "fdorg_team_id": 802,
    "team_name": "Tunisia",
    "club_season": {
      "apps": 10,
      "minutes": 316,
      "goals": 0,
      "assists": 1,
      "yellows": 0,
      "reds": 0,
      "goals_per_90": 0.0,
      "assists_per_90": 0.285,
      "form_score": 0.285
    }
  },
  {
    "tm_player_id": 526466,
    "espn_player_id": null,
    "name": "Elias Saad",
    "slug": "elias-saad",
    "position": "Left Winger",
    "age": 25,
    "market_value_m": 4.0,
    "fdorg_team_id": 802,
    "team_name": "Tunisia",
    "club_season": {
      "apps": 24,
      "minutes": 1219,
      "goals": 0,
      "assists": 4,
      "yellows": 2,
      "reds": 0,
      "goals_per_90": 0.0,
      "assists_per_90": 0.295,
      "form_score": 0.295
    }
  },
  {
    "tm_player_id": 645589,
    "espn_player_id": null,
    "name": "Elias Achouri",
    "slug": "elias-achouri",
    "position": "Left Winger",
    "age": 25,
    "market_value_m": 3.5,
    "fdorg_team_id": 802,
    "team_name": "Tunisia",
    "club_season": {
      "apps": 37,
      "minutes": 2368,
      "goals": 5,
      "assists": 7,
      "yellows": 6,
      "reds": 0,
      "goals_per_90": 0.19,
      "assists_per_90": 0.266,
      "form_score": 0.456
    }
  },
  {
    "tm_player_id": 184491,
    "espn_player_id": null,
    "name": "Naïm Sliti",
    "slug": "naim-sliti",
    "position": "Left Winger",
    "age": 32,
    "market_value_m": 2.5,
    "fdorg_team_id": 802,
    "team_name": "Tunisia",
    "club_season": {
      "apps": 17,
      "minutes": 908,
      "goals": 1,
      "assists": 3,
      "yellows": 1,
      "reds": 0,
      "goals_per_90": 0.099,
      "assists_per_90": 0.297,
      "form_score": 0.396
    }
  },
  {
    "tm_player_id": 230921,
    "espn_player_id": null,
    "name": "Mortadha Ben Ouanes",
    "slug": "mortadha-ben-ouanes",
    "position": "Left Winger",
    "age": 30,
    "market_value_m": 1.5,
    "fdorg_team_id": 802,
    "team_name": "Tunisia",
    "club_season": {
      "apps": 28,
      "minutes": 2279,
      "goals": 2,
      "assists": 6,
      "yellows": 6,
      "reds": 1,
      "goals_per_90": 0.079,
      "assists_per_90": 0.237,
      "form_score": 0.316
    }
  },
  {
    "tm_player_id": 539677,
    "espn_player_id": null,
    "name": "Sebastian Tounekti",
    "slug": "sebastian-tounekti",
    "position": "Left Winger",
    "age": 22,
    "market_value_m": 1.0,
    "fdorg_team_id": 802,
    "team_name": "Tunisia",
    "club_season": {
      "apps": 49,
      "minutes": 2941,
      "goals": 5,
      "assists": 3,
      "yellows": 5,
      "reds": 0,
      "goals_per_90": 0.153,
      "assists_per_90": 0.092,
      "form_score": 0.245
    }
  },
  {
    "tm_player_id": 569961,
    "espn_player_id": null,
    "name": "Hamza Khadhraoui",
    "slug": "hamza-khadhraoui",
    "position": "Left Winger",
    "age": 25,
    "market_value_m": 0.8,
    "fdorg_team_id": 802,
    "team_name": "Tunisia",
    "club_season": {
      "apps": 26,
      "minutes": 2185,
      "goals": 2,
      "assists": 6,
      "yellows": 8,
      "reds": 1,
      "goals_per_90": 0.082,
      "assists_per_90": 0.247,
      "form_score": 0.33
    }
  },
  {
    "tm_player_id": 1373350,
    "espn_player_id": null,
    "name": "Mohamed Rayane Anane",
    "slug": "mohamed-rayane-anane",
    "position": "Left Winger",
    "age": 18,
    "market_value_m": 0.0,
    "fdorg_team_id": 802,
    "team_name": "Tunisia",
    "club_season": {
      "apps": 30,
      "minutes": 2258,
      "goals": 6,
      "assists": 1,
      "yellows": 5,
      "reds": 0,
      "goals_per_90": 0.239,
      "assists_per_90": 0.04,
      "form_score": 0.279
    }
  },
  {
    "tm_player_id": 208880,
    "espn_player_id": null,
    "name": "Amor Layouni",
    "slug": "amor-layouni",
    "position": "Right Winger",
    "age": 32,
    "market_value_m": 0.75,
    "fdorg_team_id": 802,
    "team_name": "Tunisia",
    "club_season": {
      "apps": 23,
      "minutes": 1784,
      "goals": 1,
      "assists": 10,
      "yellows": 5,
      "reds": 0,
      "goals_per_90": 0.05,
      "assists_per_90": 0.504,
      "form_score": 0.555
    }
  },
  {
    "tm_player_id": 1198342,
    "espn_player_id": null,
    "name": "Khalil Ayari",
    "slug": "khalil-ayari",
    "position": "Right Winger",
    "age": 19,
    "market_value_m": 0.1,
    "fdorg_team_id": 802,
    "team_name": "Tunisia",
    "club_season": {
      "apps": 6,
      "minutes": 462,
      "goals": 1,
      "assists": 0,
      "yellows": 1,
      "reds": 0,
      "goals_per_90": 0.195,
      "assists_per_90": 0.0,
      "form_score": 0.195
    }
  },
  {
    "tm_player_id": 975337,
    "espn_player_id": null,
    "name": "Nacim Dendani",
    "slug": "nacim-dendani",
    "position": "Right Winger",
    "age": 18,
    "market_value_m": 0.0,
    "fdorg_team_id": 802,
    "team_name": "Tunisia",
    "club_season": {
      "apps": 2,
      "minutes": 153,
      "goals": 0,
      "assists": 0,
      "yellows": 1,
      "reds": 0,
      "goals_per_90": 0.0,
      "assists_per_90": 0.0,
      "form_score": 0.0
    }
  },
  {
    "tm_player_id": 209304,
    "espn_player_id": null,
    "name": "Seifeddine Jaziri",
    "slug": "seifeddine-jaziri",
    "position": "Centre-Forward",
    "age": 31,
    "market_value_m": 0.7,
    "fdorg_team_id": 802,
    "team_name": "Tunisia",
    "club_season": {
      "apps": 22,
      "minutes": 744,
      "goals": 4,
      "assists": 0,
      "yellows": 2,
      "reds": 0,
      "goals_per_90": 0.484,
      "assists_per_90": 0.0,
      "form_score": 0.484
    }
  },
  {
    "tm_player_id": 402087,
    "espn_player_id": null,
    "name": "Firas Chaouat",
    "slug": "firas-chaouat",
    "position": "Centre-Forward",
    "age": 28,
    "market_value_m": 0.5,
    "fdorg_team_id": 802,
    "team_name": "Tunisia",
    "club_season": {
      "apps": 26,
      "minutes": 2242,
      "goals": 14,
      "assists": 0,
      "yellows": 5,
      "reds": 0,
      "goals_per_90": 0.562,
      "assists_per_90": 0.0,
      "form_score": 0.562
    }
  },
  {
    "tm_player_id": 953150,
    "espn_player_id": null,
    "name": "Hazem Mastouri",
    "slug": "hazem-mastouri",
    "position": "Centre-Forward",
    "age": 27,
    "market_value_m": 0.4,
    "fdorg_team_id": 802,
    "team_name": "Tunisia",
    "club_season": {
      "apps": 30,
      "minutes": 1650,
      "goals": 4,
      "assists": 3,
      "yellows": 8,
      "reds": 0,
      "goals_per_90": 0.218,
      "assists_per_90": 0.164,
      "form_score": 0.382
    }
  },
  {
    "tm_player_id": 862950,
    "espn_player_id": null,
    "name": "Youssef Snana",
    "slug": "youssef-snana",
    "position": "Centre-Forward",
    "age": 20,
    "market_value_m": 0.35,
    "fdorg_team_id": 802,
    "team_name": "Tunisia",
    "club_season": {
      "apps": 18,
      "minutes": 976,
      "goals": 6,
      "assists": 2,
      "yellows": 0,
      "reds": 0,
      "goals_per_90": 0.553,
      "assists_per_90": 0.184,
      "form_score": 0.738
    }
  },
  {
    "tm_player_id": 122635,
    "espn_player_id": null,
    "name": "Issam Jebali",
    "slug": "issam-jebali",
    "position": "Centre-Forward",
    "age": 33,
    "market_value_m": 0.3,
    "fdorg_team_id": 802,
    "team_name": "Tunisia",
    "club_season": {
      "apps": 22,
      "minutes": 1519,
      "goals": 3,
      "assists": 5,
      "yellows": 1,
      "reds": 0,
      "goals_per_90": 0.178,
      "assists_per_90": 0.296,
      "form_score": 0.474
    }
  }
]